odoo/addons/mrp_bom_tracking/README.rst
odoo/addons/mrp_bom_tracking/__init__.py
odoo/addons/mrp_bom_tracking/__manifest__.py
odoo/addons/mrp_bom_tracking/i18n/mrp_bom_tracking.pot
odoo/addons/mrp_bom_tracking/models/__init__.py
odoo/addons/mrp_bom_tracking/models/mrp_bom.py
odoo/addons/mrp_bom_tracking/readme/CONTRIBUTORS.rst
odoo/addons/mrp_bom_tracking/readme/DESCRIPTION.rst
odoo/addons/mrp_bom_tracking/static/description/icon.png
odoo/addons/mrp_bom_tracking/static/description/index.html
odoo/addons/mrp_bom_tracking/views/bom_template.xml
odoo11_addon_mrp_bom_tracking-11.0.1.0.0.99.dev5.dist-info/METADATA
odoo11_addon_mrp_bom_tracking-11.0.1.0.0.99.dev5.dist-info/WHEEL
odoo11_addon_mrp_bom_tracking-11.0.1.0.0.99.dev5.dist-info/top_level.txt
odoo11_addon_mrp_bom_tracking-11.0.1.0.0.99.dev5.dist-info/RECORD
